Dift/Dift.py
Dift/__init__.py
dift-0.0.7.dist-info/METADATA
dift-0.0.7.dist-info/WHEEL
dift-0.0.7.dist-info/licenses/LICENSE
dift-0.0.7.dist-info/RECORD
