Metadata-Version: 2.1
Name: Dift
Version: 0.0.7
Summary: A library to read data from  a file and convert it into python dictionary
Project-URL: Homepage, https://github.com/NisheshTyagi/Dift
Project-URL: Bug Tracker, https://github.com/NisheshTyagi/Dift/issues
Author-email: Nishesh Tyagi <eyetrack9182@gmail.com>
License-File: LICENSE
Classifier: License :: OSI Approved :: MIT License
Classifier: Operating System :: OS Independent
Classifier: Programming Language :: Python :: 3
Requires-Python: >=3.10
